{
  "envelope": {
    "date": "2016-12-07T12:02:05+00:00",
    "model": "form",
    "owner": "dozorro.org",
    "payload": {
      "author": {
        "auth": {
          "id": "355d351008db3bf24bf16b831c0ffa78",
          "provider": "facebook",
          "scheme": "external"
        },
        "contactPoint": {
          "email": "dimus82@yandex.ru"
        },
        "name": "Дмитрий Волосовский"
      },
      "formData": {
        "correctExpectedCost": "no",
        "correctExpectedCostComment": "Очікувана ціна завищена відносно ринкової ціни в 3-4 рази!"
      },
      "tender": "d58e92bb78ce46c5878024c0a178f542"
    },
    "schema": "tender106"
  },
  "id": "56c0c8a5f58f5abdb650f02f437a65e4",
  "sign": "igtsrD8UaZED4r5tMFWpwcvLZz3btOTg2VEwHB7GW062W4m4+2MVOq/+7ag3DjMq8EYf+BW/lYSdBzQrm77rBg"
}