{
  "envelope": {
    "date": "2017-03-27T15:00:21+00:00",
    "model": "form",
    "owner": "dozorro.org",
    "payload": {
      "author": {
        "auth": {
          "id": "1d3c22879a870fc96228882b6ca7bb6b",
          "provider": "facebook",
          "scheme": "external"
        },
        "contactPoint": {
          "email": "hitman802@mail.ru"
        },
        "name": "Sergey Gonchar"
      },
      "formData": {
        "purchaserDutiesExecution": "1",
        "purchaserInteractionProblems": [
          "other"
        ]
      },
      "tender": "0ef01d6e020e40b28fca8d5ea5b832d6"
    },
    "schema": "tender112"
  },
  "id": "e19c9c64dd5e2f7a755e750a96b7919c",
  "sign": "NKXoNDAYm2FVUPNq9yZr3iFPZ++6+FWDgxX1quHsWQfc+OiwglHncLtyBcIfv3gOUcFvSZP8FgfdHKXe79IACA"
}