{
  "envelope": {
    "date": "2017-01-30T10:07:24+00:00",
    "model": "form",
    "owner": "dozorro.org",
    "payload": {
      "author": {
        "auth": {
          "id": "0fabd63ef5f817285e0e65638b525071",
          "provider": "google",
          "scheme": "external"
        },
        "contactPoint": {
          "email": "cleanstreamukr@gmail.com"
        },
        "name": "Clean Stream"
      },
      "formData": {
        "argumentativeDisqualification": "no",
        "cheapestWasDisqualified": "yes",
        "cheapestWasDisqualifiedComment": "1.)\tЗамовник не виходив на зв’язок, будь які контакти які їм було надано не відповідали.\r\n2.)\tНеобгрунтована відмова від тендеру.\r\n3.)\tЛояльність до ФОП’ів а не до виробника готової продукції. При розгляді тендерів, в більшості випадків, виграє один учасник ФОП.\r\n4.)\tВідмова та закриття тендеру, якщо переможець надав нижчу ціну, або якщо учасників більше ніж один.\r\n5.)\tПісля відмови тендеру, замовником був складений новий аналогічний тендер, який так само був відмовлений.\r\nЯкщо проаналізувати останні тендери замовника (з періоду 07.01.2017 по 30.01.2017) то складається картина, що замовник подаючи тендери допорогової суму має своїх ФОП’ів, які перемагають у тендерах майже на ті суму, які дає замовник.\r\n"
      },
      "tender": "b251372220b8498db179a50118bf17a1"
    },
    "schema": "tender111"
  },
  "id": "4133e873391f03ae20b5f5cbb526bc91",
  "sign": "wMoz+S6G6/CLhA2PwVvKnYrtgnksiOkQixyxJoKw5AENg4t/ijPKvuMKyiAeZ9Y9wCxnbnuXwwVe5gxH+cXSCg"
}