{
  "envelope": {
    "date": "2017-03-27T08:43:05+00:00",
    "model": "form",
    "owner": "dozorro.org",
    "payload": {
      "author": {
        "auth": {
          "id": "16b6cfca02ace0d9f085e2eb757e6065",
          "provider": "facebook",
          "scheme": "external"
        },
        "contactPoint": {
          "email": "garikafterwork@i.ua"
        },
        "name": "Олег Гарасимець"
      },
      "formData": {
        "purchaserDutiesExecution": "1",
        "purchaserDutiesExecutionComment": "Жах! Жахливий жах! ",
        "purchaserInteractionProblems": [
          "other"
        ],
        "purchaserInteractionProblemsComment": "Місто Київ перетворюється у пам'ятник архітектури недбальства!"
      },
      "tender": "0ef01d6e020e40b28fca8d5ea5b832d6"
    },
    "schema": "tender112"
  },
  "id": "d1ae331beb08f76bb57d73c4db73ae0c",
  "sign": "Cf8xIfIntZFRFFQhJkA6d8Sv42L5sFGUDfbuRAxniqkpGxNQCnOPTYVbyZ3ENFpPAxZBOi3sPqhJnrjOCtPsBA"
}